Metadata-Version: 2.1
Name: upsonic-phantom
Version: 0.1.0
Summary: The cloud python encryption for your applications !
Home-page: https://github.com/Upsonic/Phantom
Author: Onur Atakan ULUSOY
Author-email: onur.atakan.ulusoy@upsonic.co
License: MIT
Platform: UNKNOWN
Requires-Python: >= 3
